e_commerce/__init__.py
e_commerce/customer/__init__.py
e_commerce/customer/analysis.py
e_commerce/customer/orders.py
e_commerce/customer/personal_info.py
e_commerce/seller/__init__.py
e_commerce/seller/personal_info.py
e_commerce/seller/product_info.py
e_commerce/seller/seller_history.py
e_commerce-0.1.dist-info/LICENSE.txt
e_commerce-0.1.dist-info/METADATA
e_commerce-0.1.dist-info/WHEEL
e_commerce-0.1.dist-info/top_level.txt
e_commerce-0.1.dist-info/RECORD
