Metadata-Version: 2.1
Name: e-commerce
Version: 0.1
Summary: A python package
Home-page: https://github.com/Jagdeep14/Project_lab4.git
Author: A Sharma and J Brar
Author-email: sidhu.deepi87@gmail.com
License: MIT
Platform: UNKNOWN
